bamplot/__init__.py
bamplot/bamplot_utils.py
bamplot/annotation/hg18_refseq.ucsc.gz
bamplot/annotation/hg19_refseq.ucsc.gz
bamplot/annotation/mm10_refseq.ucsc.gz
bamplot/annotation/mm8_refseq.ucsc.gz
bamplot/annotation/mm9_refseq.ucsc.gz
bamplot/annotation/rn4_refseq.ucsc.gz
bamplot/annotation/rn6_refseq.ucsc.gz
bamplot-0.9.0.data/scripts/bamplot_plotter.R
bamplot-0.9.0.dist-info/DESCRIPTION.rst
bamplot-0.9.0.dist-info/METADATA
bamplot-0.9.0.dist-info/RECORD
bamplot-0.9.0.dist-info/WHEEL
bamplot-0.9.0.dist-info/entry_points.txt
bamplot-0.9.0.dist-info/metadata.json
bamplot-0.9.0.dist-info/top_level.txt
