Metadata-Version: 2.0
Name: bamplot
Version: 0.9.0
Summary: bamplot python package
Home-page: https://github.com/linlabbcm/bamplot
Author: UNKNOWN
Author-email: UNKNOWN
License: UNKNOWN
Download-URL: https://github.com/linlabbcm/bamplot/tarball/v0.8.0
Keywords: bioinformatics,bam,SEQ,plotting
Platform: UNKNOWN
